{
  "last_update": "2026-05-28T23:00:08.780467",
  "type": "fundamental_analysis",
  "assets_count": 6,
  "assets": {
    "US100": {
      "price": 30223.888671875,
      "change": 0.8351302723206407
    },
    "US30": {
      "price": 50668.96875,
      "change": 0.048746866162702226
    },
    "SP500": {
      "price": 7563.6298828125,
      "change": 0.57537166196686
    },
    "GOLD": {
      "price": 4525.39990234375,
      "change": 1.7515436164980327
    },
    "BTC": {
      "price": 73400.0,
      "change": -1.2707067017425795
    },
    "EURUSD": {
      "price": 1.1617909669876099,
      "change": -0.16265631135274058
    }
  }
}