{
  "last_update": "2026-03-04T10:26:14.584544",
  "type": "fundamental_analysis",
  "assets_count": 6,
  "assets": {
    "US100": {
      "price": 24720.080078125,
      "change": -1.0904009007041224
    },
    "US30": {
      "price": 48501.26953125,
      "change": -0.8250966642448686
    },
    "SP500": {
      "price": 6816.6298828125,
      "change": -0.9444031095625391
    },
    "GOLD": {
      "price": 5207.10009765625,
      "change": 1.9520734075815813
    },
    "BTC": {
      "price": 71511.0546875,
      "change": 4.711135403674413
    },
    "EURUSD": {
      "price": 1.1640088558197021,
      "change": -0.48888216269540996
    }
  }
}