{
  "last_update": "2026-04-22T21:33:51.464197",
  "type": "fundamental_analysis",
  "assets_count": 6,
  "assets": {
    "US100": {
      "price": 26937.275390625,
      "change": 1.7289042240786625
    },
    "US30": {
      "price": 49490.03125,
      "change": 0.6930959278239862
    },
    "SP500": {
      "price": 7137.89990234375,
      "change": 1.0460084168953927
    },
    "GOLD": {
      "price": 4758.2998046875,
      "change": 1.274900042328656
    },
    "BTC": {
      "price": 78695.9765625,
      "change": 3.0689168441511465
    },
    "EURUSD": {
      "price": 1.1709601879119873,
      "change": -0.6346590676311129
    }
  }
}