{
  "last_update": "2026-03-30T14:09:04.552171",
  "type": "fundamental_analysis",
  "assets_count": 6,
  "assets": {
    "US100": {
      "price": 23151.9140625,
      "change": 0.08275935669586687
    },
    "US30": {
      "price": 45354.390625,
      "change": 0.415682896496135
    },
    "SP500": {
      "price": 6382.35986328125,
      "change": 0.21212252475484739
    },
    "GOLD": {
      "price": 4551.89990234375,
      "change": 1.3334795713212377
    },
    "BTC": {
      "price": 67495.9609375,
      "change": 2.3365035067748687
    },
    "EURUSD": {
      "price": 1.1463946104049683,
      "change": -0.6167624415649107
    }
  }
}