{
  "last_update": "2026-04-09T23:56:58.304339",
  "type": "fundamental_analysis",
  "assets_count": 6,
  "assets": {
    "US100": {
      "price": 25082.0859375,
      "change": 0.7184467527077336
    },
    "US30": {
      "price": 48185.80078125,
      "change": 0.5758283367060907
    },
    "SP500": {
      "price": 6824.66015625,
      "change": 0.6170023529293196
    },
    "GOLD": {
      "price": 4785.2001953125,
      "change": 0.7516621815454259
    },
    "BTC": {
      "price": 71800.3125,
      "change": 0.9518013926068153
    },
    "EURUSD": {
      "price": 1.1694538593292236,
      "change": 0.30172034787303004
    }
  }
}