{
  "last_update": "2026-03-01T09:48:46.265984",
  "type": "fundamental_analysis",
  "assets_count": 6,
  "assets": {
    "US100": {
      "price": 24960.0390625,
      "change": -0.2969121279128998
    },
    "US30": {
      "price": 48977.921875,
      "change": -1.053102579389897
    },
    "SP500": {
      "price": 6878.8798828125,
      "change": -0.4339352811031182
    },
    "GOLD": {
      "price": 5247.89990234375,
      "change": 1.379308458297112
    },
    "BTC": {
      "price": 66333.03125,
      "change": -0.9893568515778144
    },
    "EURUSD": {
      "price": 1.1803030967712402,
      "change": -0.10269109594141139
    }
  }
}