{
  "last_update": "2026-04-08T21:27:30.779878",
  "type": "fundamental_analysis",
  "assets_count": 6,
  "assets": {
    "US100": {
      "price": 24903.166015625,
      "change": 2.895571383644728
    },
    "US30": {
      "price": 47909.921875,
      "change": 2.845285554078437
    },
    "SP500": {
      "price": 6782.81005859375,
      "change": 2.5081414644149875
    },
    "GOLD": {
      "price": 4745.0,
      "change": 1.8874385454585105
    },
    "BTC": {
      "price": 71647.921875,
      "change": -0.40697579712458504
    },
    "EURUSD": {
      "price": 1.1665889024734497,
      "change": 1.0802697234748728
    }
  }
}