{
  "last_update": "2026-04-02T07:56:53.858584",
  "type": "fundamental_analysis",
  "assets_count": 6,
  "assets": {
    "US100": {
      "price": 24019.990234375,
      "change": 1.1785954017025289
    },
    "US30": {
      "price": 46565.73828125,
      "change": 0.48385681472984154
    },
    "SP500": {
      "price": 6575.31982421875,
      "change": 0.7168516684867307
    },
    "GOLD": {
      "price": 4663.10009765625,
      "change": -2.510873322298891
    },
    "BTC": {
      "price": 66900.296875,
      "change": -1.730732707103639
    },
    "EURUSD": {
      "price": 1.15340256690979,
      "change": -0.3471673985021756
    }
  }
}