{
  "last_update": "2026-06-25T01:58:53.108600",
  "type": "fundamental_analysis",
  "assets_count": 6,
  "assets": {
    "US100": {
      "price": 29220.056640625,
      "change": -0.4334743662933932
    },
    "US30": {
      "price": 51848.8984375,
      "change": 0.3523702906943382
    },
    "SP500": {
      "price": 7358.22021484375,
      "change": -0.09829319733113452
    },
    "GOLD": {
      "price": 3999.0,
      "change": -3.1695659807508485
    },
    "BTC": {
      "price": 60805.01171875,
      "change": -2.9728206291424186
    },
    "EURUSD": {
      "price": 1.1361054182052612,
      "change": -0.1624684732174771
    }
  }
}