{
  "last_update": "2026-03-13T11:59:38.167801",
  "type": "fundamental_analysis",
  "assets_count": 6,
  "assets": {
    "US100": {
      "price": 24533.58203125,
      "change": -1.7281296439508889
    },
    "US30": {
      "price": 46677.8515625,
      "change": -1.5593853801781903
    },
    "SP500": {
      "price": 6672.6201171875,
      "change": -1.5227676506708516
    },
    "GOLD": {
      "price": 5100.60009765625,
      "change": -0.2971130148080233
    },
    "BTC": {
      "price": 72298.15625,
      "change": 2.5600889621521854
    },
    "EURUSD": {
      "price": 1.1471836566925049,
      "change": -0.6183319722057331
    }
  }
}