{
  "last_update": "2026-04-15T18:47:54.193064",
  "type": "fundamental_analysis",
  "assets_count": 6,
  "assets": {
    "US100": {
      "price": 26111.7421875,
      "change": 1.0438131239842119
    },
    "US30": {
      "price": 48438.26171875,
      "change": -0.20134866098472518
    },
    "SP500": {
      "price": 7014.7099609375,
      "change": 0.6793095671696664
    },
    "GOLD": {
      "price": 4818.10009765625,
      "change": -0.1430031573834197
    },
    "BTC": {
      "price": 74357.59375,
      "change": 0.23723450661520515
    },
    "EURUSD": {
      "price": 1.1800801753997803,
      "change": 0.2714122706302953
    }
  }
}