{
  "last_update": "2026-02-11T08:05:20.193499",
  "type": "fundamental_analysis",
  "assets_count": 6,
  "assets": {
    "US100": {
      "price": 25127.640625,
      "change": -0.5560361646119341
    },
    "US30": {
      "price": 50188.140625,
      "change": 0.10425575562905895
    },
    "SP500": {
      "price": 6941.81005859375,
      "change": -0.33037129754582023
    },
    "GOLD": {
      "price": 5078.5,
      "change": 1.492869383833497
    },
    "BTC": {
      "price": 67001.7734375,
      "change": -2.6051523645051056
    },
    "EURUSD": {
      "price": 1.1921793222427368,
      "change": 0.14902095406257096
    }
  }
}